odin/__init__.py
odin/adapters.py
odin/annotated_resource/__init__.py
odin/annotated_resource/special_fields.py
odin/annotated_resource/type_aliases.py
odin/annotated_resource/type_resolution.py
odin/bases.py
odin/codecs/__init__.py
odin/codecs/csv_codec.py
odin/codecs/dict_codec.py
odin/codecs/json_codec.py
odin/codecs/msgpack_codec.py
odin/codecs/toml_codec.py
odin/codecs/xml_codec.py
odin/codecs/yaml_codec.py
odin/compatibility.py
odin/contrib/__init__.py
odin/contrib/arrow/__init__.py
odin/contrib/arrow/fields.py
odin/contrib/geo/__init__.py
odin/contrib/geo/datatypes.py
odin/contrib/geo/fields.py
odin/contrib/json_schema/__init__.py
odin/contrib/money/__init__.py
odin/contrib/money/datatypes.py
odin/contrib/money/fields.py
odin/contrib/pint/__init__.py
odin/contrib/pint/fields.py
odin/contrib/pint/units.py
odin/contrib/rich/__init__.py
odin/contrib/rich/theme.py
odin/contrib/rich/validation_tree.py
odin/contrib/sphinx/__init__.py
odin/contrib/swagger/__init__.py
odin/datastructures.py
odin/datetimeutil.py
odin/decorators.py
odin/exceptions.py
odin/fields/__init__.py
odin/fields/base.py
odin/fields/composite.py
odin/fields/virtual.py
odin/filtering.py
odin/helpers.py
odin/mapping/__init__.py
odin/mapping/helpers.py
odin/proxy.py
odin/py.typed
odin/registration.py
odin/resources.py
odin/serializers.py
odin/traversal.py
odin/utils/__init__.py
odin/utils/ipv6.py
odin/validators.py
odin-2.10.dist-info/AUTHORS
odin-2.10.dist-info/LICENSE
odin-2.10.dist-info/METADATA
odin-2.10.dist-info/WHEEL
odin-2.10.dist-info/RECORD
