Metadata-Version: 2.1
Name: odin
Version: 2.10
Summary: Data-structure definition/validation/traversal, mapping and serialisation toolkit for Python
Home-page: https://github.com/python-odin/odin
License: BSD-3-Clause
Keywords: data-structure,validation,data-mapping
Author: Tim Savage
Author-email: tim@savage.company
Requires-Python: >=3.8,<4.0
Classifier: Development Status :: 5 - Production/Stable
Classifier: Intended Audience :: Developers
Classifier: License :: OSI Approved :: BSD License
Classifier: Operating System :: OS Independent
Classifier: Programming Language :: Python
Classifier: Programming Language :: Python :: 3
Classifier: Programming Language :: Python :: 3.8
Classifier: Programming Language :: Python :: 3.9
Classifier: Programming Language :: Python :: 3.10
Classifier: Programming Language :: Python :: 3.11
Classifier: Programming Language :: Python :: 3.12
Classifier: Programming Language :: Python :: Implementation :: CPython
Classifier: Programming Language :: Python :: Implementation :: PyPy
Classifier: Topic :: Software Development :: Libraries :: Application Frameworks
Classifier: Topic :: Software Development :: Libraries :: Python Modules
Provides-Extra: arrow
Provides-Extra: msgpack
Provides-Extra: pint
Provides-Extra: rich
Provides-Extra: toml
Provides-Extra: yaml
Requires-Dist: arrow ; extra == "arrow"
Requires-Dist: msgpack ; extra == "msgpack"
Requires-Dist: pint ; extra == "pint"
Requires-Dist: pyyaml ; extra == "yaml"
Requires-Dist: rich ; extra == "rich"
Requires-Dist: toml ; extra == "toml"
Project-URL: Documentation, https://odin.readthedocs.org
Project-URL: Repository, https://github.com/python-odin/odin
